akahu/__init__.py
akahu/akahu.py
akahu/decorators.py
akahu/rest_adapter.py
akahu/utils.py
akahu/models/__init__.py
akahu/models/account.py
akahu/models/payment.py
akahu/models/transaction.py
akahu_py-0.1.0.dist-info/licenses/LICENSE
akahu_py-0.1.0.dist-info/METADATA
akahu_py-0.1.0.dist-info/WHEEL
akahu_py-0.1.0.dist-info/top_level.txt
akahu_py-0.1.0.dist-info/RECORD
