Metadata-Version: 2.4
Name: Akahu.py
Version: 0.1.0
Summary: An unofficial simple object oriented wrapper written in python for the Akahu open banking API.
Author: Trouty_
License: GPLv3
Requires-Python: >=3.8
License-File: LICENSE
Requires-Dist: requests<=2.32.3
Provides-Extra: docs
Requires-Dist: Sphinx<=8.2.3; extra == "docs"
Requires-Dist: sphinxawesome-theme<=5.3.2; extra == "docs"
Dynamic: license-file
